{"built":1784675022,"n_arrivals_window":332969,"n_promises_window":1857366,"n_resolutions_window":334746,"record_begins":"2026-07-13","today":{"n_arrivals":41043,"n_promises":232060,"worst_miss":20.0,"kept_share":0.663},"last_burst":1784675013,"burst_stats":{"mbta":{"snapshots":30,"promises":40840,"resolved":1170,"errors":0},"bart":{"snapshots":30,"promises":18447,"resolved":416,"errors":0}},"engine_counters":{"resolved":351679,"rejected":160967,"stale":0},"pending_pairs":2111,"agencies":["mbta","bart"]}