{"built":1784559301,"n_arrivals_window":251254,"n_promises_window":1400347,"n_resolutions_window":253006,"record_begins":"2026-07-13","today":{"n_arrivals":15566,"n_promises":95205,"worst_miss":20.0,"kept_share":0.62},"last_burst":1784559293,"burst_stats":{"mbta":{"snapshots":30,"promises":45691,"resolved":1087,"errors":0},"bart":{"snapshots":30,"promises":18308,"resolved":404,"errors":0}},"engine_counters":{"resolved":268455,"rejected":134167,"stale":0},"pending_pairs":2208,"agencies":["mbta","bart"]}