[{"agency":"mbta","route":"Green-B","stop":"70117","issued":1784208143,"promised_min":20,"predicted":1784209343,"actual":1784209412,"err_min":1.1,"kept":false,"verdict":"late"},{"agency":"bart","route":"system","stop":"M90-2","issued":1784209042,"promised_min":5,"predicted":1784209342,"actual":1784209410,"err_min":1.1,"kept":false,"verdict":"late"},{"agency":"mbta","route":"Green-E","stop":"70260","issued":1784207783,"promised_min":30,"predicted":1784209583,"actual":1784209406,"err_min":-2.9,"kept":false,"verdict":"early"},{"agency":"mbta","route":"Green-B","stop":"71150","issued":1784208861,"promised_min":8,"predicted":1784209341,"actual":1784209400,"err_min":1.0,"kept":true,"verdict":"kept"},{"agency":"mbta","route":"Orange","stop":"70026","issued":1784207449,"promised_min":30,"predicted":1784209249,"actual":1784209396,"err_min":2.5,"kept":false,"verdict":"late"},{"agency":"mbta","route":"Mattapan","stop":"70264","issued":1784208022,"promised_min":20,"predicted":1784209222,"actual":1784209395,"err_min":2.9,"kept":false,"verdict":"late"},{"agency":"mbta","route":"Red","stop":"Braintree-02","issued":1784208983,"promised_min":5,"predicted":1784209283,"actual":1784209394,"err_min":1.8,"kept":false,"verdict":"late"},{"agency":"mbta","route":"Orange","stop":"70027","issued":1784207569,"promised_min":30,"predicted":1784209369,"actual":1784209390,"err_min":0.4,"kept":true,"verdict":"kept"},{"agency":"mbta","route":"Green-E","stop":"70243","issued":1784207149,"promised_min":30,"predicted":1784208949,"actual":1784209390,"err_min":7.4,"kept":false,"verdict":"late"},{"agency":"mbta","route":"Red","stop":"70075","issued":1784207389,"promised_min":30,"predicted":1784209189,"actual":1784209389,"err_min":3.3,"kept":false,"verdict":"late"},{"agency":"mbta","route":"Blue","stop":"70055","issued":1784207963,"promised_min":20,"predicted":1784209163,"actual":1784209387,"err_min":3.7,"kept":false,"verdict":"late"},{"agency":"bart","route":"system","stop":"S20-1","issued":1784209102,"promised_min":5,"predicted":1784209402,"actual":1784209386,"err_min":-0.3,"kept":true,"verdict":"kept"},{"agency":"mbta","route":"Green-C","stop":"70217","issued":1784208383,"promised_min":15,"predicted":1784209283,"actual":1784209384,"err_min":1.7,"kept":false,"verdict":"late"},{"agency":"bart","route":"system","stop":"A60-1","issued":1784208742,"promised_min":10,"predicted":1784209342,"actual":1784209383,"err_min":0.7,"kept":true,"verdict":"kept"},{"agency":"mbta","route":"Red","stop":"Alewife-02","issued":1784209102,"promised_min":5,"predicted":1784209402,"actual":1784209380,"err_min":-0.4,"kept":true,"verdict":"kept"},{"agency":"mbta","route":"Green-B","stop":"70157","issued":1784209103,"promised_min":5,"predicted":1784209403,"actual":1784209379,"err_min":-0.4,"kept":true,"verdict":"kept"},{"agency":"bart","route":"system","stop":"A10-1","issued":1784207568,"promised_min":30,"predicted":1784209368,"actual":1784209376,"err_min":0.1,"kept":true,"verdict":"kept"},{"agency":"bart","route":"system","stop":"C30-1","issued":1784209163,"promised_min":3,"predicted":1784209343,"actual":1784209376,"err_min":0.5,"kept":true,"verdict":"kept"},{"agency":"mbta","route":"Orange","stop":"70013","issued":1784207509,"promised_min":30,"predicted":1784209309,"actual":1784209374,"err_min":1.1,"kept":false,"verdict":"late"},{"agency":"mbta","route":"Red","stop":"70096","issued":1784207963,"promised_min":20,"predicted":1784209163,"actual":1784209373,"err_min":3.5,"kept":false,"verdict":"late"},{"agency":"mbta","route":"Mattapan","stop":"70269","issued":1784208443,"promised_min":15,"predicted":1784209343,"actual":1784209373,"err_min":0.5,"kept":true,"verdict":"kept"},{"agency":"mbta","route":"Orange","stop":"70030","issued":1784208143,"promised_min":20,"predicted":1784209343,"actual":1784209372,"err_min":0.5,"kept":true,"verdict":"kept"},{"agency":"bart","route":"system","stop":"K30-1","issued":1784208863,"promised_min":8,"predicted":1784209343,"actual":1784209369,"err_min":0.4,"kept":true,"verdict":"kept"},{"agency":"mbta","route":"Orange","stop":"70018","issued":1784207209,"promised_min":30,"predicted":1784209009,"actual":1784209369,"err_min":6.0,"kept":false,"verdict":"late"},{"agency":"mbta","route":"Red","stop":"70088","issued":1784207569,"promised_min":30,"predicted":1784209369,"actual":1784209369,"err_min":0.0,"kept":true,"verdict":"kept"},{"agency":"mbta","route":"Green-D","stop":"70178","issued":1784208082,"promised_min":20,"predicted":1784209282,"actual":1784209368,"err_min":1.4,"kept":false,"verdict":"late"},{"agency":"mbta","route":"Red","stop":"70100","issued":1784207329,"promised_min":30,"predicted":1784209129,"actual":1784209365,"err_min":3.9,"kept":false,"verdict":"late"},{"agency":"bart","route":"system","stop":"W10-2","issued":1784209043,"promised_min":5,"predicted":1784209343,"actual":1784209364,"err_min":0.3,"kept":true,"verdict":"kept"},{"agency":"mbta","route":"Green-E","stop":"70206","issued":1784208262,"promised_min":15,"predicted":1784209162,"actual":1784209362,"err_min":3.3,"kept":false,"verdict":"late"},{"agency":"mbta","route":"Green-D","stop":"70172","issued":1784208741,"promised_min":10,"predicted":1784209341,"actual":1784209361,"err_min":0.3,"kept":true,"verdict":"kept"},{"agency":"mbta","route":"Red","stop":"70067","issued":1784207389,"promised_min":30,"predicted":1784209189,"actual":1784209360,"err_min":2.9,"kept":false,"verdict":"late"},{"agency":"bart","route":"system","stop":"M16-1","issued":1784209043,"promised_min":5,"predicted":1784209343,"actual":1784209357,"err_min":0.2,"kept":true,"verdict":"kept"},{"agency":"mbta","route":"Green-E","stop":"70208","issued":1784208923,"promised_min":8,"predicted":1784209403,"actual":1784209357,"err_min":-0.8,"kept":true,"verdict":"kept"},{"agency":"mbta","route":"Green-E","stop":"70257","issued":1784207783,"promised_min":30,"predicted":1784209583,"actual":1784209355,"err_min":-3.8,"kept":false,"verdict":"early"},{"agency":"mbta","route":"Green-D","stop":"70151","issued":1784208023,"promised_min":20,"predicted":1784209223,"actual":1784209355,"err_min":2.2,"kept":false,"verdict":"late"},{"agency":"mbta","route":"Green-C","stop":"70155","issued":1784208622,"promised_min":8,"predicted":1784209102,"actual":1784209353,"err_min":4.2,"kept":false,"verdict":"late"},{"agency":"mbta","route":"Green-E","stop":"70159","issued":1784208082,"promised_min":20,"predicted":1784209282,"actual":1784209350,"err_min":1.1,"kept":false,"verdict":"late"},{"agency":"mbta","route":"Orange","stop":"70010","issued":1784207148,"promised_min":30,"predicted":1784208948,"actual":1784209349,"err_min":6.7,"kept":false,"verdict":"late"},{"agency":"bart","route":"system","stop":"A30-2","issued":1784209163,"promised_min":3,"predicted":1784209343,"actual":1784209348,"err_min":0.1,"kept":true,"verdict":"kept"},{"agency":"mbta","route":"Blue","stop":"70047","issued":1784207903,"promised_min":20,"predicted":1784209103,"actual":1784209348,"err_min":4.1,"kept":false,"verdict":"late"},{"agency":"bart","route":"system","stop":"Y10-2","issued":1784209103,"promised_min":3,"predicted":1784209283,"actual":1784209346,"err_min":1.0,"kept":true,"verdict":"kept"},{"agency":"mbta","route":"Blue","stop":"70056","issued":1784207449,"promised_min":30,"predicted":1784209249,"actual":1784209345,"err_min":1.6,"kept":false,"verdict":"late"},{"agency":"mbta","route":"Blue","stop":"70041","issued":1784207389,"promised_min":30,"predicted":1784209189,"actual":1784209345,"err_min":2.6,"kept":false,"verdict":"late"},{"agency":"mbta","route":"Mattapan","stop":"70272","issued":1784209102,"promised_min":3,"predicted":1784209282,"actual":1784209344,"err_min":1.0,"kept":true,"verdict":"kept"},{"agency":"bart","route":"system","stop":"M40-2","issued":1784208863,"promised_min":8,"predicted":1784209343,"actual":1784209343,"err_min":0.0,"kept":true,"verdict":"kept"},{"agency":"mbta","route":"Orange","stop":"70001","issued":1784207268,"promised_min":30,"predicted":1784209068,"actual":1784209343,"err_min":4.6,"kept":false,"verdict":"late"},{"agency":"mbta","route":"Green-E","stop":"70258","issued":1784208983,"promised_min":3,"predicted":1784209163,"actual":1784209343,"err_min":3.0,"kept":false,"verdict":"late"},{"agency":"mbta","route":"Orange","stop":"70033","issued":1784207508,"promised_min":30,"predicted":1784209308,"actual":1784209340,"err_min":0.5,"kept":true,"verdict":"kept"}]