{"generated":1784812511,"max_unc_s":120,"agencies":{"bart":{"horizons":[{"h":1,"n":31026,"mean_wait":1.05,"median_err":0.38,"bias":0.05,"within_1min":0.992},{"h":2,"n":35403,"mean_wait":2.09,"median_err":0.37,"bias":0.09,"within_1min":0.975},{"h":3,"n":32661,"mean_wait":3.16,"median_err":0.37,"bias":0.16,"within_1min":0.939},{"h":5,"n":16969,"mean_wait":5.35,"median_err":0.43,"bias":0.35,"within_1min":0.872},{"h":8,"n":11138,"mean_wait":8.7,"median_err":0.58,"bias":0.7,"within_1min":0.732},{"h":10,"n":8931,"mean_wait":10.84,"median_err":0.7,"bias":0.84,"within_1min":0.662},{"h":15,"n":7649,"mean_wait":16.17,"median_err":1.0,"bias":1.17,"within_1min":0.504},{"h":20,"n":6106,"mean_wait":21.39,"median_err":1.22,"bias":1.39,"within_1min":0.432},{"h":30,"n":2835,"mean_wait":32.07,"median_err":2.0,"bias":2.07,"within_1min":0.239}],"median_abs_err":0.43,"bias":0.36,"within_1min":0.865,"n_promises":152718,"n_arrivals":91913,"coverage":0.995,"excluded_outliers":199,"routes":{"":{"horizons":[]},"system":{"horizons":[{"h":1,"n":31008,"mean_wait":1.05,"median_err":0.38,"bias":0.05,"within_1min":0.992},{"h":2,"n":35396,"mean_wait":2.09,"median_err":0.37,"bias":0.09,"within_1min":0.975},{"h":3,"n":32661,"mean_wait":3.16,"median_err":0.37,"bias":0.16,"within_1min":0.939},{"h":5,"n":16969,"mean_wait":5.35,"median_err":0.43,"bias":0.35,"within_1min":0.872},{"h":8,"n":11138,"mean_wait":8.7,"median_err":0.58,"bias":0.7,"within_1min":0.732},{"h":10,"n":8931,"mean_wait":10.84,"median_err":0.7,"bias":0.84,"within_1min":0.662},{"h":15,"n":7649,"mean_wait":16.17,"median_err":1.0,"bias":1.17,"within_1min":0.504},{"h":20,"n":6106,"mean_wait":21.39,"median_err":1.22,"bias":1.39,"within_1min":0.432},{"h":30,"n":2835,"mean_wait":32.07,"median_err":2.0,"bias":2.07,"within_1min":0.239}],"median_abs_err":0.43,"bias":0.36,"within_1min":0.864,"n_promises":152693}},"by_hour_utc":[{"hour":0,"median_err":0.42,"bias":0.35,"n":8082},{"hour":1,"median_err":0.4,"bias":0.19,"n":7170},{"hour":2,"median_err":0.38,"bias":0.17,"n":7444},{"hour":3,"median_err":0.42,"bias":0.28,"n":5625},{"hour":4,"median_err":0.4,"bias":0.26,"n":4675},{"hour":5,"median_err":0.4,"bias":0.23,"n":4464},{"hour":6,"median_err":0.4,"bias":0.2,"n":4501},{"hour":7,"median_err":0.4,"bias":0.2,"n":3770},{"hour":8,"median_err":0.48,"bias":0.8,"n":1154},{"hour":11,"median_err":0.38,"bias":0.15,"n":391},{"hour":12,"median_err":0.4,"bias":0.19,"n":5049},{"hour":13,"median_err":0.4,"bias":0.17,"n":6654},{"hour":14,"median_err":0.4,"bias":0.2,"n":7919},{"hour":15,"median_err":0.4,"bias":0.21,"n":8242},{"hour":16,"median_err":0.42,"bias":0.28,"n":8355},{"hour":17,"median_err":0.4,"bias":0.23,"n":8066},{"hour":18,"median_err":0.4,"bias":0.22,"n":7452},{"hour":19,"median_err":0.4,"bias":0.22,"n":7453},{"hour":20,"median_err":0.4,"bias":0.2,"n":7119},{"hour":21,"median_err":0.4,"bias":0.21,"n":7115},{"hour":22,"median_err":0.38,"bias":0.2,"n":7567},{"hour":23,"median_err":0.4,"bias":0.26,"n":7858}]},"mbta":{"horizons":[{"h":1,"n":288955,"mean_wait":1.22,"median_err":0.32,"bias":0.22,"within_1min":0.936},{"h":2,"n":278501,"mean_wait":2.33,"median_err":0.37,"bias":0.33,"within_1min":0.879},{"h":3,"n":270931,"mean_wait":3.44,"median_err":0.43,"bias":0.44,"within_1min":0.818},{"h":5,"n":259714,"mean_wait":5.64,"median_err":0.58,"bias":0.64,"within_1min":0.708},{"h":8,"n":245160,"mean_wait":8.94,"median_err":0.82,"bias":0.94,"within_1min":0.578},{"h":10,"n":235069,"mean_wait":11.15,"median_err":0.98,"bias":1.15,"within_1min":0.508},{"h":15,"n":217205,"mean_wait":16.61,"median_err":1.4,"bias":1.61,"within_1min":0.385},{"h":20,"n":194304,"mean_wait":22.09,"median_err":1.85,"bias":2.09,"within_1min":0.307},{"h":30,"n":155656,"mean_wait":32.78,"median_err":2.48,"bias":2.78,"within_1min":0.245}],"median_abs_err":0.63,"bias":0.99,"within_1min":0.635,"n_promises":2145495,"n_arrivals":322322,"coverage":0.995,"excluded_outliers":2147,"routes":{"Blue":{"horizons":[{"h":1,"n":30151,"mean_wait":1.22,"median_err":0.3,"bias":0.22,"within_1min":0.94},{"h":2,"n":28637,"mean_wait":2.33,"median_err":0.32,"bias":0.33,"within_1min":0.898},{"h":3,"n":28327,"mean_wait":3.5,"median_err":0.38,"bias":0.5,"within_1min":0.835},{"h":5,"n":27857,"mean_wait":5.74,"median_err":0.52,"bias":0.74,"within_1min":0.739},{"h":8,"n":28029,"mean_wait":9.15,"median_err":0.78,"bias":1.15,"within_1min":0.591},{"h":10,"n":27216,"mean_wait":11.47,"median_err":1.0,"bias":1.47,"within_1min":0.501},{"h":15,"n":26618,"mean_wait":17.1,"median_err":1.62,"bias":2.1,"within_1min":0.345},{"h":20,"n":25350,"mean_wait":22.76,"median_err":2.3,"bias":2.76,"within_1min":0.245},{"h":30,"n":21494,"mean_wait":33.39,"median_err":2.87,"bias":3.39,"within_1min":0.205}],"median_abs_err":0.65,"bias":1.32,"within_1min":0.609,"n_promises":243679},"Green-B":{"horizons":[{"h":1,"n":36130,"mean_wait":1.25,"median_err":0.35,"bias":0.25,"within_1min":0.907},{"h":2,"n":35151,"mean_wait":2.36,"median_err":0.47,"bias":0.36,"within_1min":0.818},{"h":3,"n":34370,"mean_wait":3.47,"median_err":0.57,"bias":0.47,"within_1min":0.74},{"h":5,"n":32118,"mean_wait":5.67,"median_err":0.78,"bias":0.67,"within_1min":0.607},{"h":8,"n":29777,"mean_wait":8.97,"median_err":1.1,"bias":0.97,"within_1min":0.467},{"h":10,"n":28453,"mean_wait":11.16,"median_err":1.32,"bias":1.16,"within_1min":0.4},{"h":15,"n":24733,"mean_wait":16.61,"median_err":1.87,"bias":1.61,"within_1min":0.287},{"h":20,"n":21348,"mean_wait":22.01,"median_err":2.37,"bias":2.01,"within_1min":0.228},{"h":30,"n":14416,"mean_wait":32.18,"median_err":2.98,"bias":2.18,"within_1min":0.179}],"median_abs_err":0.82,"bias":0.92,"within_1min":0.57,"n_promises":256496},"Green-C":{"horizons":[{"h":1,"n":32863,"mean_wait":1.22,"median_err":0.33,"bias":0.22,"within_1min":0.928},{"h":2,"n":31660,"mean_wait":2.3,"median_err":0.43,"bias":0.3,"within_1min":0.845},{"h":3,"n":30282,"mean_wait":3.39,"median_err":0.52,"bias":0.39,"within_1min":0.767},{"h":5,"n":28090,"mean_wait":5.55,"median_err":0.75,"bias":0.55,"within_1min":0.625},{"h":8,"n":24873,"mean_wait":8.77,"median_err":1.02,"bias":0.77,"within_1min":0.494},{"h":10,"n":23098,"mean_wait":10.91,"median_err":1.18,"bias":0.91,"within_1min":0.439},{"h":15,"n":19385,"mean_wait":16.1,"median_err":1.52,"bias":1.1,"within_1min":0.355},{"h":20,"n":15792,"mean_wait":21.37,"median_err":1.88,"bias":1.37,"within_1min":0.292},{"h":30,"n":8646,"mean_wait":31.17,"median_err":2.53,"bias":1.17,"within_1min":0.221}],"median_abs_err":0.7,"bias":0.64,"within_1min":0.624,"n_promises":214689},"Green-D":{"horizons":[{"h":1,"n":40641,"mean_wait":1.21,"median_err":0.3,"bias":0.21,"within_1min":0.951},{"h":2,"n":39263,"mean_wait":2.3,"median_err":0.37,"bias":0.3,"within_1min":0.898},{"h":3,"n":38220,"mean_wait":3.4,"median_err":0.43,"bias":0.4,"within_1min":0.839},{"h":5,"n":36209,"mean_wait":5.59,"median_err":0.6,"bias":0.59,"within_1min":0.714},{"h":8,"n":33826,"mean_wait":8.86,"median_err":0.85,"bias":0.86,"within_1min":0.57},{"h":10,"n":32055,"mean_wait":11.06,"median_err":1.02,"bias":1.06,"within_1min":0.494},{"h":15,"n":28599,"mean_wait":16.49,"median_err":1.45,"bias":1.49,"within_1min":0.369},{"h":20,"n":24922,"mean_wait":21.9,"median_err":1.87,"bias":1.9,"within_1min":0.291},{"h":30,"n":17914,"mean_wait":32.68,"median_err":2.62,"bias":2.68,"within_1min":0.207}],"median_abs_err":0.63,"bias":0.88,"within_1min":0.646,"n_promises":291649},"Green-E":{"horizons":[{"h":1,"n":42372,"mean_wait":1.27,"median_err":0.33,"bias":0.27,"within_1min":0.916},{"h":2,"n":41398,"mean_wait":2.4,"median_err":0.42,"bias":0.4,"within_1min":0.844},{"h":3,"n":39957,"mean_wait":3.53,"median_err":0.53,"bias":0.53,"within_1min":0.755},{"h":5,"n":38378,"mean_wait":5.76,"median_err":0.77,"bias":0.76,"within_1min":0.612},{"h":8,"n":36519,"mean_wait":9.09,"median_err":1.1,"bias":1.09,"within_1min":0.468},{"h":10,"n":35493,"mean_wait":11.32,"median_err":1.33,"bias":1.32,"within_1min":0.398},{"h":15,"n":32995,"mean_wait":16.84,"median_err":1.85,"bias":1.84,"within_1min":0.295},{"h":20,"n":30292,"mean_wait":22.37,"median_err":2.38,"bias":2.37,"within_1min":0.23},{"h":30,"n":24961,"mean_wait":33.49,"median_err":3.57,"bias":3.49,"within_1min":0.145}],"median_abs_err":0.83,"bias":1.19,"within_1min":0.555,"n_promises":322365},"Mattapan":{"horizons":[{"h":1,"n":12984,"mean_wait":1.26,"median_err":0.28,"bias":0.26,"within_1min":0.957},{"h":2,"n":11763,"mean_wait":2.41,"median_err":0.37,"bias":0.41,"within_1min":0.912},{"h":3,"n":10888,"mean_wait":3.5,"median_err":0.5,"bias":0.5,"within_1min":0.828},{"h":5,"n":9362,"mean_wait":5.74,"median_err":0.7,"bias":0.74,"within_1min":0.683},{"h":8,"n":7902,"mean_wait":9.02,"median_err":0.93,"bias":1.02,"within_1min":0.543},{"h":10,"n":6715,"mean_wait":11.06,"median_err":0.98,"bias":1.06,"within_1min":0.514},{"h":15,"n":5873,"mean_wait":16.43,"median_err":1.27,"bias":1.43,"within_1min":0.412},{"h":20,"n":2676,"mean_wait":21.7,"median_err":1.5,"bias":1.7,"within_1min":0.341}],"median_abs_err":0.55,"bias":0.72,"within_1min":0.728,"n_promises":68163},"Orange":{"horizons":[{"h":1,"n":54203,"mean_wait":1.16,"median_err":0.28,"bias":0.16,"within_1min":0.962},{"h":2,"n":51937,"mean_wait":2.23,"median_err":0.3,"bias":0.23,"within_1min":0.942},{"h":3,"n":51513,"mean_wait":3.3,"median_err":0.32,"bias":0.3,"within_1min":0.919},{"h":5,"n":51472,"mean_wait":5.44,"median_err":0.38,"bias":0.44,"within_1min":0.863},{"h":8,"n":49808,"mean_wait":8.66,"median_err":0.52,"bias":0.66,"within_1min":0.765},{"h":10,"n":48558,"mean_wait":10.8,"median_err":0.6,"bias":0.8,"within_1min":0.7},{"h":15,"n":46498,"mean_wait":16.16,"median_err":0.87,"bias":1.16,"within_1min":0.556},{"h":20,"n":44127,"mean_wait":21.47,"median_err":1.1,"bias":1.47,"within_1min":0.467},{"h":30,"n":41316,"mean_wait":31.92,"median_err":1.38,"bias":1.92,"within_1min":0.393}],"median_abs_err":0.47,"bias":0.75,"within_1min":0.746,"n_promises":439432},"Red":{"horizons":[{"h":1,"n":39611,"mean_wait":1.24,"median_err":0.32,"bias":0.24,"within_1min":0.928},{"h":2,"n":38692,"mean_wait":2.41,"median_err":0.36,"bias":0.41,"within_1min":0.867},{"h":3,"n":37374,"mean_wait":3.51,"median_err":0.4,"bias":0.51,"within_1min":0.821},{"h":5,"n":36228,"mean_wait":5.79,"median_err":0.55,"bias":0.79,"within_1min":0.718},{"h":8,"n":34426,"mean_wait":9.17,"median_err":0.8,"bias":1.17,"within_1min":0.585},{"h":10,"n":33481,"mean_wait":11.46,"median_err":1.0,"bias":1.46,"within_1min":0.501},{"h":15,"n":32504,"mean_wait":17.09,"median_err":1.52,"bias":2.09,"within_1min":0.366},{"h":20,"n":29797,"mean_wait":22.82,"median_err":2.13,"bias":2.82,"within_1min":0.272},{"h":30,"n":26888,"mean_wait":33.86,"median_err":3.1,"bias":3.86,"within_1min":0.21}],"median_abs_err":0.67,"bias":1.35,"within_1min":0.614,"n_promises":309001}},"by_hour_utc":[{"hour":0,"median_err":0.48,"bias":0.55,"n":70891},{"hour":1,"median_err":0.48,"bias":0.63,"n":61897},{"hour":2,"median_err":0.48,"bias":0.55,"n":70185},{"hour":3,"median_err":0.47,"bias":0.49,"n":70106},{"hour":4,"median_err":0.47,"bias":0.46,"n":59210},{"hour":5,"median_err":0.47,"bias":0.51,"n":17741},{"hour":6,"median_err":0.55,"bias":0.93,"n":1788},{"hour":8,"median_err":0.52,"bias":1.0,"n":528},{"hour":9,"median_err":0.45,"bias":0.5,"n":48480},{"hour":10,"median_err":0.45,"bias":0.58,"n":95197},{"hour":11,"median_err":0.47,"bias":0.6,"n":103933},{"hour":12,"median_err":0.48,"bias":0.61,"n":100338},{"hour":13,"median_err":0.48,"bias":0.58,"n":88651},{"hour":14,"median_err":0.52,"bias":0.73,"n":84820},{"hour":15,"median_err":0.5,"bias":0.64,"n":80991},{"hour":16,"median_err":0.5,"bias":0.57,"n":78536},{"hour":17,"median_err":0.48,"bias":0.6,"n":77666},{"hour":18,"median_err":0.5,"bias":0.64,"n":74351},{"hour":19,"median_err":0.48,"bias":0.59,"n":79322},{"hour":20,"median_err":0.52,"bias":0.63,"n":77538},{"hour":21,"median_err":0.52,"bias":0.69,"n":76757},{"hour":22,"median_err":0.52,"bias":0.65,"n":79221},{"hour":23,"median_err":0.48,"bias":0.56,"n":80138}]}},"window_days":30}