{"generated":1784404877,"max_unc_s":120,"agencies":{"bart":{"horizons":[{"h":1,"n":13667,"mean_wait":1.05,"median_err":0.38,"bias":0.05,"within_1min":0.993},{"h":2,"n":15809,"mean_wait":2.1,"median_err":0.37,"bias":0.1,"within_1min":0.977},{"h":3,"n":14755,"mean_wait":3.15,"median_err":0.37,"bias":0.15,"within_1min":0.943},{"h":5,"n":7543,"mean_wait":5.35,"median_err":0.45,"bias":0.35,"within_1min":0.87},{"h":8,"n":4917,"mean_wait":8.69,"median_err":0.58,"bias":0.69,"within_1min":0.738},{"h":10,"n":3876,"mean_wait":10.82,"median_err":0.68,"bias":0.82,"within_1min":0.665},{"h":15,"n":3259,"mean_wait":16.15,"median_err":0.97,"bias":1.15,"within_1min":0.515},{"h":20,"n":2594,"mean_wait":21.38,"median_err":1.27,"bias":1.38,"within_1min":0.424},{"h":30,"n":1170,"mean_wait":32.03,"median_err":2.02,"bias":2.03,"within_1min":0.235}],"median_abs_err":0.43,"bias":0.35,"within_1min":0.869,"n_promises":67590,"n_arrivals":41271,"coverage":0.992,"excluded_outliers":108,"routes":{"":{"horizons":[]},"system":{"horizons":[{"h":1,"n":13649,"mean_wait":1.05,"median_err":0.38,"bias":0.05,"within_1min":0.993},{"h":2,"n":15802,"mean_wait":2.1,"median_err":0.37,"bias":0.1,"within_1min":0.977},{"h":3,"n":14755,"mean_wait":3.15,"median_err":0.37,"bias":0.15,"within_1min":0.943},{"h":5,"n":7543,"mean_wait":5.35,"median_err":0.45,"bias":0.35,"within_1min":0.87},{"h":8,"n":4917,"mean_wait":8.69,"median_err":0.58,"bias":0.69,"within_1min":0.738},{"h":10,"n":3876,"mean_wait":10.82,"median_err":0.68,"bias":0.82,"within_1min":0.665},{"h":15,"n":3259,"mean_wait":16.15,"median_err":0.97,"bias":1.15,"within_1min":0.515},{"h":20,"n":2594,"mean_wait":21.38,"median_err":1.27,"bias":1.38,"within_1min":0.424},{"h":30,"n":1170,"mean_wait":32.03,"median_err":2.02,"bias":2.03,"within_1min":0.235}],"median_abs_err":0.43,"bias":0.35,"within_1min":0.869,"n_promises":67565}},"by_hour_utc":[{"hour":0,"median_err":0.43,"bias":0.46,"n":3405},{"hour":1,"median_err":0.42,"bias":0.24,"n":2686},{"hour":2,"median_err":0.4,"bias":0.15,"n":3281},{"hour":3,"median_err":0.42,"bias":0.28,"n":2392},{"hour":4,"median_err":0.4,"bias":0.26,"n":2003},{"hour":5,"median_err":0.4,"bias":0.26,"n":2139},{"hour":6,"median_err":0.4,"bias":0.23,"n":2269},{"hour":7,"median_err":0.42,"bias":0.24,"n":2028},{"hour":8,"median_err":0.47,"bias":0.88,"n":613},{"hour":11,"median_err":0.37,"bias":0.21,"n":167},{"hour":12,"median_err":0.38,"bias":0.18,"n":2026},{"hour":13,"median_err":0.38,"bias":0.15,"n":3582},{"hour":14,"median_err":0.4,"bias":0.2,"n":4344},{"hour":15,"median_err":0.4,"bias":0.19,"n":4500},{"hour":16,"median_err":0.4,"bias":0.21,"n":4522},{"hour":17,"median_err":0.4,"bias":0.18,"n":3863},{"hour":18,"median_err":0.4,"bias":0.18,"n":3350},{"hour":19,"median_err":0.4,"bias":0.19,"n":3425},{"hour":20,"median_err":0.4,"bias":0.15,"n":2277},{"hour":21,"median_err":0.38,"bias":0.17,"n":2243},{"hour":22,"median_err":0.4,"bias":0.19,"n":2612},{"hour":23,"median_err":0.4,"bias":0.31,"n":2837}]},"mbta":{"horizons":[{"h":1,"n":126628,"mean_wait":1.24,"median_err":0.32,"bias":0.24,"within_1min":0.931},{"h":2,"n":122112,"mean_wait":2.36,"median_err":0.37,"bias":0.36,"within_1min":0.872},{"h":3,"n":118441,"mean_wait":3.47,"median_err":0.43,"bias":0.47,"within_1min":0.811},{"h":5,"n":112946,"mean_wait":5.68,"median_err":0.58,"bias":0.68,"within_1min":0.701},{"h":8,"n":105793,"mean_wait":9.01,"median_err":0.83,"bias":1.01,"within_1min":0.57},{"h":10,"n":101124,"mean_wait":11.23,"median_err":1.02,"bias":1.23,"within_1min":0.499},{"h":15,"n":92174,"mean_wait":16.75,"median_err":1.47,"bias":1.75,"within_1min":0.371},{"h":20,"n":82466,"mean_wait":22.29,"median_err":1.95,"bias":2.29,"within_1min":0.29},{"h":30,"n":64095,"mean_wait":33.09,"median_err":2.68,"bias":3.09,"within_1min":0.224}],"median_abs_err":0.65,"bias":1.07,"within_1min":0.63,"n_promises":925779,"n_arrivals":141436,"coverage":0.992,"excluded_outliers":1210,"routes":{"Blue":{"horizons":[{"h":1,"n":12549,"mean_wait":1.25,"median_err":0.3,"bias":0.25,"within_1min":0.933},{"h":2,"n":11908,"mean_wait":2.37,"median_err":0.33,"bias":0.37,"within_1min":0.889},{"h":3,"n":11715,"mean_wait":3.56,"median_err":0.4,"bias":0.56,"within_1min":0.821},{"h":5,"n":11427,"mean_wait":5.82,"median_err":0.53,"bias":0.82,"within_1min":0.718},{"h":8,"n":11422,"mean_wait":9.26,"median_err":0.83,"bias":1.26,"within_1min":0.568},{"h":10,"n":11076,"mean_wait":11.61,"median_err":1.07,"bias":1.61,"within_1min":0.479},{"h":15,"n":10766,"mean_wait":17.3,"median_err":1.72,"bias":2.3,"within_1min":0.326},{"h":20,"n":10191,"mean_wait":23.05,"median_err":2.45,"bias":3.05,"within_1min":0.231},{"h":30,"n":8358,"mean_wait":33.81,"median_err":3.17,"bias":3.81,"within_1min":0.191}],"median_abs_err":0.68,"bias":1.44,"within_1min":0.597,"n_promises":99412},"Green-B":{"horizons":[{"h":1,"n":16045,"mean_wait":1.26,"median_err":0.35,"bias":0.26,"within_1min":0.903},{"h":2,"n":15528,"mean_wait":2.37,"median_err":0.47,"bias":0.37,"within_1min":0.815},{"h":3,"n":15217,"mean_wait":3.48,"median_err":0.57,"bias":0.48,"within_1min":0.736},{"h":5,"n":14140,"mean_wait":5.69,"median_err":0.78,"bias":0.69,"within_1min":0.607},{"h":8,"n":12992,"mean_wait":9.01,"median_err":1.08,"bias":1.01,"within_1min":0.472},{"h":10,"n":12401,"mean_wait":11.22,"median_err":1.3,"bias":1.22,"within_1min":0.404},{"h":15,"n":10660,"mean_wait":16.73,"median_err":1.88,"bias":1.73,"within_1min":0.291},{"h":20,"n":9073,"mean_wait":22.21,"median_err":2.42,"bias":2.21,"within_1min":0.224},{"h":30,"n":5741,"mean_wait":32.53,"median_err":3.05,"bias":2.53,"within_1min":0.173}],"median_abs_err":0.8,"bias":0.97,"within_1min":0.574,"n_promises":111797},"Green-C":{"horizons":[{"h":1,"n":13547,"mean_wait":1.22,"median_err":0.33,"bias":0.22,"within_1min":0.926},{"h":2,"n":13039,"mean_wait":2.3,"median_err":0.43,"bias":0.3,"within_1min":0.843},{"h":3,"n":12416,"mean_wait":3.4,"median_err":0.52,"bias":0.4,"within_1min":0.766},{"h":5,"n":11428,"mean_wait":5.57,"median_err":0.73,"bias":0.57,"within_1min":0.63},{"h":8,"n":9952,"mean_wait":8.79,"median_err":1.0,"bias":0.79,"within_1min":0.505},{"h":10,"n":9174,"mean_wait":10.93,"median_err":1.15,"bias":0.93,"within_1min":0.447},{"h":15,"n":7540,"mean_wait":16.16,"median_err":1.52,"bias":1.16,"within_1min":0.352},{"h":20,"n":5934,"mean_wait":21.46,"median_err":1.93,"bias":1.46,"within_1min":0.277},{"h":30,"n":2792,"mean_wait":31.21,"median_err":2.67,"bias":1.21,"within_1min":0.215}],"median_abs_err":0.68,"bias":0.65,"within_1min":0.632,"n_promises":85822},"Green-D":{"horizons":[{"h":1,"n":17620,"mean_wait":1.21,"median_err":0.3,"bias":0.21,"within_1min":0.95},{"h":2,"n":17056,"mean_wait":2.29,"median_err":0.37,"bias":0.29,"within_1min":0.901},{"h":3,"n":16618,"mean_wait":3.4,"median_err":0.42,"bias":0.4,"within_1min":0.844},{"h":5,"n":15680,"mean_wait":5.58,"median_err":0.58,"bias":0.58,"within_1min":0.727},{"h":8,"n":14600,"mean_wait":8.84,"median_err":0.82,"bias":0.84,"within_1min":0.588},{"h":10,"n":13787,"mean_wait":11.04,"median_err":0.97,"bias":1.04,"within_1min":0.516},{"h":15,"n":12327,"mean_wait":16.48,"median_err":1.37,"bias":1.48,"within_1min":0.392},{"h":20,"n":10730,"mean_wait":21.89,"median_err":1.77,"bias":1.89,"within_1min":0.308},{"h":30,"n":7656,"mean_wait":32.62,"median_err":2.43,"bias":2.62,"within_1min":0.227}],"median_abs_err":0.62,"bias":0.87,"within_1min":0.659,"n_promises":126074},"Green-E":{"horizons":[{"h":1,"n":18082,"mean_wait":1.27,"median_err":0.33,"bias":0.27,"within_1min":0.916},{"h":2,"n":17541,"mean_wait":2.4,"median_err":0.42,"bias":0.4,"within_1min":0.846},{"h":3,"n":16839,"mean_wait":3.52,"median_err":0.53,"bias":0.52,"within_1min":0.754},{"h":5,"n":15972,"mean_wait":5.74,"median_err":0.77,"bias":0.74,"within_1min":0.613},{"h":8,"n":14985,"mean_wait":9.08,"median_err":1.1,"bias":1.08,"within_1min":0.47},{"h":10,"n":14471,"mean_wait":11.31,"median_err":1.32,"bias":1.31,"within_1min":0.403},{"h":15,"n":13250,"mean_wait":16.86,"median_err":1.83,"bias":1.86,"within_1min":0.298},{"h":20,"n":12085,"mean_wait":22.4,"median_err":2.37,"bias":2.4,"within_1min":0.232},{"h":30,"n":9625,"mean_wait":33.64,"median_err":3.67,"bias":3.64,"within_1min":0.141}],"median_abs_err":0.82,"bias":1.18,"within_1min":0.564,"n_promises":132850},"Mattapan":{"horizons":[{"h":1,"n":5544,"mean_wait":1.35,"median_err":0.28,"bias":0.35,"within_1min":0.939},{"h":2,"n":4999,"mean_wait":2.51,"median_err":0.38,"bias":0.51,"within_1min":0.89},{"h":3,"n":4541,"mean_wait":3.6,"median_err":0.5,"bias":0.6,"within_1min":0.809},{"h":5,"n":3809,"mean_wait":5.88,"median_err":0.7,"bias":0.88,"within_1min":0.659},{"h":8,"n":3036,"mean_wait":9.19,"median_err":0.98,"bias":1.19,"within_1min":0.511},{"h":10,"n":2357,"mean_wait":11.18,"median_err":1.05,"bias":1.18,"within_1min":0.484},{"h":15,"n":1871,"mean_wait":16.53,"median_err":1.33,"bias":1.53,"within_1min":0.408},{"h":20,"n":846,"mean_wait":21.9,"median_err":1.6,"bias":1.9,"within_1min":0.298}],"median_abs_err":0.55,"bias":0.79,"within_1min":0.724,"n_promises":27003},"Orange":{"horizons":[{"h":1,"n":22567,"mean_wait":1.2,"median_err":0.3,"bias":0.2,"within_1min":0.952},{"h":2,"n":21568,"mean_wait":2.3,"median_err":0.32,"bias":0.3,"within_1min":0.927},{"h":3,"n":21306,"mean_wait":3.37,"median_err":0.33,"bias":0.37,"within_1min":0.902},{"h":5,"n":21120,"mean_wait":5.54,"median_err":0.4,"bias":0.54,"within_1min":0.84},{"h":8,"n":20065,"mean_wait":8.81,"median_err":0.53,"bias":0.81,"within_1min":0.734},{"h":10,"n":19350,"mean_wait":10.97,"median_err":0.65,"bias":0.97,"within_1min":0.669},{"h":15,"n":18078,"mean_wait":16.4,"median_err":0.97,"bias":1.4,"within_1min":0.518},{"h":20,"n":16751,"mean_wait":21.74,"median_err":1.22,"bias":1.74,"within_1min":0.431},{"h":30,"n":14693,"mean_wait":32.24,"median_err":1.52,"bias":2.24,"within_1min":0.365}],"median_abs_err":0.47,"bias":0.87,"within_1min":0.73,"n_promises":175498},"Red":{"horizons":[{"h":1,"n":20674,"mean_wait":1.25,"median_err":0.32,"bias":0.25,"within_1min":0.927},{"h":2,"n":20473,"mean_wait":2.43,"median_err":0.37,"bias":0.43,"within_1min":0.86},{"h":3,"n":19789,"mean_wait":3.54,"median_err":0.42,"bias":0.54,"within_1min":0.813},{"h":5,"n":19370,"mean_wait":5.81,"median_err":0.57,"bias":0.81,"within_1min":0.709},{"h":8,"n":18741,"mean_wait":9.21,"median_err":0.83,"bias":1.21,"within_1min":0.572},{"h":10,"n":18508,"mean_wait":11.51,"median_err":1.05,"bias":1.51,"within_1min":0.488},{"h":15,"n":17682,"mean_wait":17.19,"median_err":1.62,"bias":2.19,"within_1min":0.343},{"h":20,"n":16856,"mean_wait":22.9,"median_err":2.23,"bias":2.9,"within_1min":0.255},{"h":30,"n":15223,"mean_wait":33.98,"median_err":3.27,"bias":3.98,"within_1min":0.179}],"median_abs_err":0.72,"bias":1.43,"within_1min":0.594,"n_promises":167316}},"by_hour_utc":[{"hour":0,"median_err":0.48,"bias":0.56,"n":29110},{"hour":1,"median_err":0.47,"bias":0.53,"n":22947},{"hour":2,"median_err":0.48,"bias":0.6,"n":31398},{"hour":3,"median_err":0.47,"bias":0.55,"n":31156},{"hour":4,"median_err":0.45,"bias":0.54,"n":26431},{"hour":5,"median_err":0.48,"bias":0.56,"n":8613},{"hour":6,"median_err":0.53,"bias":0.87,"n":933},{"hour":8,"median_err":0.52,"bias":1.42,"n":278},{"hour":9,"median_err":0.45,"bias":0.49,"n":25432},{"hour":10,"median_err":0.45,"bias":0.62,"n":43992},{"hour":11,"median_err":0.48,"bias":0.67,"n":47158},{"hour":12,"median_err":0.48,"bias":0.67,"n":43793},{"hour":13,"median_err":0.48,"bias":0.62,"n":44748},{"hour":14,"median_err":0.52,"bias":0.73,"n":44071},{"hour":15,"median_err":0.5,"bias":0.67,"n":42355},{"hour":16,"median_err":0.5,"bias":0.57,"n":42573},{"hour":17,"median_err":0.5,"bias":0.63,"n":36456},{"hour":18,"median_err":0.5,"bias":0.7,"n":31973},{"hour":19,"median_err":0.48,"bias":0.61,"n":34844},{"hour":20,"median_err":0.53,"bias":0.74,"n":23559},{"hour":21,"median_err":0.6,"bias":0.93,"n":22795},{"hour":22,"median_err":0.54,"bias":0.75,"n":25558},{"hour":23,"median_err":0.48,"bias":0.57,"n":26858}]}},"window_days":30}